data_df_summarizer/__init__.py
data_df_summarizer-0.1.0.dist-info/METADATA
data_df_summarizer-0.1.0.dist-info/WHEEL
data_df_summarizer-0.1.0.dist-info/top_level.txt
data_df_summarizer-0.1.0.dist-info/RECORD
