Metadata-Version: 2.4
Name: data_df_summarizer
Version: 0.1.0
Summary: A simple DataFrame summarizer to get summary of huge datasets in just one line of code.
Author: anushhhka-jain
Author-email: anushkaj2211@gmail.com
Classifier: Programming Language :: Python :: 3
Classifier: License :: OSI Approved :: MIT License
Classifier: Operating System :: OS Independent
Requires-Python: >=3.6
Requires-Dist: pandas
Dynamic: author
Dynamic: author-email
Dynamic: classifier
Dynamic: description
Dynamic: description-content-type
Dynamic: requires-dist
Dynamic: requires-python
Dynamic: summary
